{
    "Groceries": [
        {
            "id": 1,
            "name": "Banana Blossom",
            "description": "Flower of the banana tree. *Great deep fried*",
            "image": "/images/banana-blossom.jpg"
        },
        {
            "id": 2,
            "name": "Banana Blossom",
            "description": "Flower of the banana tree. *Great deep fried*",
            "image": "/images/banana-blossom.jpg"
        },
        {
            "id": 3,
            "name": "Banana Blossom",
            "description": "Flower of the banana tree. *Great deep fried*",
            "image": "/images/banana-blossom.jpg"
        },
        {
            "id": 4,
            "name": "Banana Blossom",
            "description": "Flower of the banana tree. *Great deep fried*",
            "image": "/images/banana-blossom.jpg"
        },
        {
            "id": 5,
            "name": "Banana Blossom",
            "description": "Flower of the banana tree. *Great deep fried*",
            "image": "/images/banana-blossom.jpg"
        },
        {
            "id": 6,
            "name": "Banana Blossom",
            "description": "Flower of the banana tree. *Great deep fried*",
            "image": "/images/banana-blossom.jpg"
        },
        {
            "id": 7,
            "name": "Banana Blossom",
            "description": "Flower of the banana tree. *Great deep fried*",
            "image": "/images/banana-blossom.jpg"
        }
    ]
}